cellniche/__init__.py
cellniche/main.py
cellniche/model.py
cellniche/sampler.py
cellniche/trainer.py
cellniche/utils.py
cellniche-0.1.5.dist-info/licenses/LICENSE
cellniche-0.1.5.dist-info/METADATA
cellniche-0.1.5.dist-info/WHEEL
cellniche-0.1.5.dist-info/top_level.txt
cellniche-0.1.5.dist-info/RECORD
