Metadata-Version: 2.4
Name: CellNiche
Version: 0.1.5
Summary: CellNiche represents cellular microenvironments in atlas-scale spatial omics data with contrastive learning
Author-email: Zhongming Liang <liangzhongming21@mails.ucas.ac.cn>
License: 
Project-URL: Homepage, https://github.com/Super-LzzZ/CellNiche
Project-URL: Issues, https://github.com/Super-LzzZ/CellNiche/issues
Classifier: Programming Language :: Python :: 3
Classifier: License :: OSI Approved :: MIT License
Classifier: Operating System :: OS Independent
Requires-Python: >=3.7
License-File: LICENSE
Requires-Dist: torch>=1.12.1
Requires-Dist: torch-geometric>=2.6.1
Requires-Dist: torch-scatter>=2.1.0
Requires-Dist: torch-sparse>=0.6.15
Requires-Dist: torch-cluster>=1.6.0
Requires-Dist: torch-spline-conv>=1.2.1
Requires-Dist: scanpy>=1.9.8
Requires-Dist: anndata>=0.9.2
Requires-Dist: scikit-learn>=1.3.2
Requires-Dist: numpy>=1.22.4
Requires-Dist: scipy>=1.10.1
Requires-Dist: pandas>=2.0.3
Requires-Dist: tqdm>=4.67.1
Requires-Dist: networkx>=3.1
Requires-Dist: node2vec>=0.5.0
Requires-Dist: h5py>=3.11.0
Requires-Dist: natsort>=8.4.0
Dynamic: license-file
